jtrends.py
jtrends-0.0.2.dist-info/METADATA
jtrends-0.0.2.dist-info/WHEEL
jtrends-0.0.2.dist-info/entry_points.txt
jtrends-0.0.2.dist-info/top_level.txt
jtrends-0.0.2.dist-info/RECORD
