Metadata-Version: 2.1
Name: jtrends
Version: 0.0.2
Summary: This Python script fetches Google Trends data for specific keywords over the past 7 days in Japan and plots the relative interest over time, handling rate limits by pausing for 60 seconds if necessary.
Home-page: https://github.com/ishishishi/jtrends
Author: takahiro ishii
Author-email: ishii.takahiro.761@outlook.jp
Project-URL: Bug Tracker, https://github.com/ishishishi/jtrends
Classifier: Programming Language :: Python :: 3
Classifier: License :: OSI Approved :: MIT License
Classifier: Operating System :: OS Independent
Requires-Python: >=3.7
